vbdataset/__init__.py
vbdataset/fetch.py
vbdataset_test-0.0.0.3.dist-info/METADATA
vbdataset_test-0.0.0.3.dist-info/WHEEL
vbdataset_test-0.0.0.3.dist-info/top_level.txt
vbdataset_test-0.0.0.3.dist-info/RECORD
